appiepy/__init__.py
appiepy/__main__.py
appiepy/__private.py
appiepy-0.2.4.dist-info/LICENSE
appiepy-0.2.4.dist-info/METADATA
appiepy-0.2.4.dist-info/WHEEL
appiepy-0.2.4.dist-info/top_level.txt
appiepy-0.2.4.dist-info/RECORD
