Metadata-Version: 2.1
Name: appiepy
Version: 0.2.4
Summary: A Python API for Albert Heijn
Home-page: https://github.com/rkalis/AppiePy
Author: Rosco Kalis
Author-email: roscokalis@gmail.com
License: MIT
Project-URL: GitHub, https://github.com/rkalis/AppiePy
Project-URL: Issues, https://github.com/rkalis/AppiePy/issues
Keywords: albert heijn products API nutrition price
Platform: UNKNOWN
Classifier: Development Status :: 3 - Alpha
Classifier: Intended Audience :: Developers
Classifier: License :: OSI Approved :: MIT License
Classifier: Operating System :: OS Independent
Classifier: Programming Language :: Python :: 3
Classifier: Programming Language :: Python :: 3.4
Classifier: Programming Language :: Python :: 3.5
Classifier: Programming Language :: Python :: 3.6
Classifier: Programming Language :: Python :: 3.7
Classifier: Programming Language :: Python :: 3.8
Requires-Python: ~=3.4
Requires-Dist: requests
Provides-Extra: dev
Requires-Dist: twine ; extra == 'dev'
Provides-Extra: test
Requires-Dist: nose ; extra == 'test'
Requires-Dist: coverage ; extra == 'test'
